blueprints/__init__.py
blueprints/api.py
blueprints/auth.py
blueprints/dashboard.py
blueprints/media.py
blueprints/rooms.py
blueprints/spaces.py
blueprints/users.py
config/__init__.py
config/settings.py
core/__init__.py
core/context.py
core/filters.py
core/security.py
ept_mx_adm-1.0.1.dist-info/licenses/LICENSE
modules/__init__.py
modules/analytics.py
modules/auth.py
modules/media.py
modules/rooms.py
modules/spaces.py
modules/system.py
modules/users.py
utils/__init__.py
utils/api_client.py
utils/i18n.py
utils/logger.py
ept_mx_adm-1.0.1.dist-info/METADATA
ept_mx_adm-1.0.1.dist-info/WHEEL
ept_mx_adm-1.0.1.dist-info/entry_points.txt
ept_mx_adm-1.0.1.dist-info/top_level.txt
ept_mx_adm-1.0.1.dist-info/RECORD
