Metadata-Version: 2.4
Name: ept-mx-adm
Version: 1.0.1
Summary: Web-Based Administration Panel for Matrix Synapse Server
Home-page: https://github.com/EPTLLC/EPT-MX-ADM
Author: Brabus (EasyProTech LLC)
Author-email: support@easypro.tech
Project-URL: Bug Reports, https://github.com/EPTLLC/EPT-MX-ADM/issues
Project-URL: Source, https://github.com/EPTLLC/EPT-MX-ADM
Project-URL: Documentation, https://github.com/EPTLLC/EPT-MX-ADM/blob/main/README.md
Project-URL: Changelog, https://github.com/EPTLLC/EPT-MX-ADM/blob/main/CHANGELOG.md
Project-URL: Telegram, https://t.me/EasyProTech
Keywords: matrix,synapse,admin,administration,panel,web,flask,matrix-synapse,admin-panel,chat,communication,server-management,user-management,room-management
Classifier: Development Status :: 5 - Production/Stable
Classifier: Intended Audience :: System Administrators
Classifier: Intended Audience :: Information Technology
Classifier: Topic :: System :: Systems Administration
Classifier: Topic :: Communications :: Chat
Classifier: License :: OSI Approved :: MIT License
Classifier: Programming Language :: Python :: 3
Classifier: Programming Language :: Python :: 3.8
Classifier: Programming Language :: Python :: 3.9
Classifier: Programming Language :: Python :: 3.10
Classifier: Programming Language :: Python :: 3.11
Classifier: Programming Language :: Python :: 3.12
Classifier: Operating System :: OS Independent
Classifier: Framework :: Flask
Classifier: Environment :: Web Environment
Classifier: Natural Language :: English
Classifier: Natural Language :: Russian
Classifier: Natural Language :: German
Classifier: Natural Language :: French
Classifier: Natural Language :: Italian
Classifier: Natural Language :: Spanish
Classifier: Natural Language :: Turkish
Requires-Python: >=3.8
License-File: LICENSE
Requires-Dist: Flask==3.1.1
Requires-Dist: Flask-WTF==1.2.2
Requires-Dist: requests==2.32.4
Requires-Dist: Werkzeug==3.1.3
Requires-Dist: Jinja2==3.1.6
Requires-Dist: gunicorn==23.0.0
Requires-Dist: psutil==6.1.1
Requires-Dist: urllib3==2.5.0
Requires-Dist: certifi==2024.8.30
Requires-Dist: Flask-Limiter==3.8.0
Dynamic: author
Dynamic: author-email
Dynamic: classifier
Dynamic: description
Dynamic: description-content-type
Dynamic: home-page
Dynamic: keywords
Dynamic: license-file
Dynamic: project-url
Dynamic: requires-dist
Dynamic: requires-python
Dynamic: summary
